{
  "name_zh": "铜镜怪",
  "name_ja": "ドーミラー",
  "name_en": "Bronzor",
  "pokedex_id": "0436",
  "description": "铜镜怪（日文︰ドーミラー，英文︰Bronzor）是钢属性／超能力属性宝可梦。",
  "profile": "铜镜怪像是一个古代铜镜，呈青铜色。周围镶有六个铜珠，中间有同心圆图案，圆心两侧有一双黄色的眼睛。它的背部有一个类似树的图案，有五片树叶，一片在上方，两旁各有两片。\n铜镜怪靠着不可思议的能量漂浮在半空。它能在古墓找到，身上的纹路不属于伽勒尔文化，因此至今仍然谜团重重。从古墓里挖掘出了与铜镜怪一模一样的道具，但两者之间的关系还未知。据说它背上的花纹蕴藏着神秘的力量，人们将其视为神圣，相同纹路有时会被刻在古时的坟墓等地。为了调查它的身体构造而用Ｘ光拍摄了照片，但照片上却空无一物。有研究者认为这种宝可梦在过去会像镜子一样反射。虽然人们说把铜镜怪打磨到发光，它就能映照出真相，但其实它非常讨厌被打磨。",
  "prototype": "铜镜怪的原型可能为铜镜。\n结合其进化型及曾经的专属特性耐热来看，可能也参考了“无间之钟”的日本传说，该传说亦被小泉八云的《怪谈》收录。\n其背部的图案可能是“农业”的象征，意指人类刚刚从狩猎时期转到农耕时期，暗示了铜镜被创造的时间。\n铜镜怪家族的异色可能来源于铜绿。",
  "detail": "如果您在寻找此宝可梦在Pokémon GO里的资料，请移步铜镜怪（Pokémon GO）。\n←\nNo.0435：坦克臭鼬\n宝可梦\nNo.0437：青铜钟\n→",
  "names": [
    {
      "language": "日文",
      "name": "ドーミラー Dohmirror",
      "origin": "来自“銅（どう）鏡（きょう）”（铜镜）和英文 mirror（镜子）。"
    },
    {
      "language": "中文-任天堂",
      "name": "銅鏡怪铜镜怪",
      "origin": "来自“铜镜”和“怪”。"
    },
    {
      "language": "中文-大陆",
      "name": "铜镜怪",
      "origin": "来自“铜镜”和“怪”。"
    },
    {
      "language": "中文-台湾",
      "name": "銅鏡怪",
      "origin": "来自“铜镜”和“怪”。"
    },
    {
      "language": "中文-香港",
      "name": "銅鏡怪",
      "origin": "来自“铜镜”和“怪”。"
    },
    {
      "language": "英文",
      "name": "Bronzor",
      "origin": "来自 bronze（青铜）和 mirror（镜子）。"
    },
    {
      "language": "法文",
      "name": "Archéomire",
      "origin": "来自 archéologie（考古学）和 miroir（镜子）。"
    },
    {
      "language": "德文",
      "name": "Bronzel",
      "origin": "来自 Bronze（青铜）和 Spiegel（镜子）。"
    },
    {
      "language": "意大利文",
      "name": "Bronzor",
      "origin": "同英文名。"
    },
    {
      "language": "西班牙文",
      "name": "Bronzor",
      "origin": "同英文名。"
    },
    {
      "language": "韩文",
      "name": "동미러 Dongmirror",
      "origin": "来自“동〈銅〉”（铜）和英文 mirror（镜子）。"
    }
  ],
  "forms": [
    {
      "name": "铜镜怪",
      "types": [
        "钢",
        "超能力"
      ],
      "category": "青铜宝可梦",
      "abilities": [
        {
          "name": "飘浮",
          "is_hidden": false
        },
        {
          "name": "耐热",
          "is_hidden": false
        },
        {
          "name": "重金属",
          "is_hidden": true
        }
      ],
      "height": "0.5m",
      "weight": "60.5kg",
      "color": "绿色",
      "catch_rate": "255（33.3%）",
      "egg_groups": [
        "矿物群"
      ],
      "experience_100": "1,000,000（较快）",
      "gender_ratio": {
        "male": 0,
        "female": 0
      },
      "egg_cycles": "20 孵化周期（5140步）",
      "shape": "Body01.png",
      "footprint": "F436.png",
      "image": "0436-铜镜怪.png"
    }
  ],
  "stats": [
    {
      "form": "一般",
      "data": {
        "hp": "57",
        "attack": "24",
        "defense": "86",
        "sp_attack": "24",
        "sp_defense": "86",
        "speed": "23"
      }
    }
  ],
  "type_effectiveness": [
    {
      "type": "一般",
      "damage": "0.5"
    },
    {
      "type": "格斗",
      "damage": "1"
    },
    {
      "type": "飞行",
      "damage": "0.5"
    },
    {
      "type": "毒",
      "damage": "0"
    },
    {
      "type": "地面",
      "damage": "2"
    },
    {
      "type": "岩石",
      "damage": "0.5"
    },
    {
      "type": "虫",
      "damage": "1"
    },
    {
      "type": "幽灵",
      "damage": "2"
    },
    {
      "type": "钢",
      "damage": "0.5"
    },
    {
      "type": "火",
      "damage": "2"
    },
    {
      "type": "水",
      "damage": "1"
    },
    {
      "type": "草",
      "damage": "0.5"
    },
    {
      "type": "电",
      "damage": "1"
    },
    {
      "type": "超能力",
      "damage": "0.25"
    },
    {
      "type": "冰",
      "damage": "0.5"
    },
    {
      "type": "龙",
      "damage": "0.5"
    },
    {
      "type": "恶",
      "damage": "2"
    },
    {
      "type": "妖精",
      "damage": "0.5"
    }
  ],
  "pokedex_entries": [
    {
      "name": "第四世代",
      "versions": [
        {
          "name": "钻石",
          "group": "宝可梦 钻石／珍珠",
          "text": "从古墓里挖掘出了与铜镜怪一模一样的道具，但两者之间的关系还未知。"
        },
        {
          "name": "珍珠",
          "group": "宝可梦 钻石／珍珠",
          "text": "为了调查它的身体构造而用Ｘ光拍摄了照片，但照片上却空无一物。"
        },
        {
          "name": "白金",
          "group": "宝可梦 白金",
          "text": "有研究者认为这种宝可梦在过去会像镜子一样反射。"
        },
        {
          "name": "心金",
          "group": "宝可梦 心金／魂银",
          "text": "过去的人们相信，铜镜怪背上的花纹里蕴藏着神秘的力量。"
        },
        {
          "name": "魂银",
          "group": "宝可梦 心金／魂银",
          "text": "过去的人们相信，铜镜怪背上的花纹里蕴藏着神秘的力量。"
        }
      ]
    },
    {
      "name": "第五世代",
      "versions": [
        {
          "name": "黑",
          "group": "宝可梦 黑／白",
          "text": "有研究者认为这种宝可梦在过去会像镜子一样反射。"
        },
        {
          "name": "白",
          "group": "宝可梦 黑／白",
          "text": "有研究者认为这种宝可梦在过去会像镜子一样反射。"
        }
      ]
    },
    {
      "name": "第六世代",
      "versions": [
        {
          "name": "Ｘ",
          "group": "宝可梦 Ｘ／Ｙ",
          "text": "过去的人们相信，铜镜怪背上的花纹里蕴藏着神秘的力量。"
        },
        {
          "name": "Ｙ",
          "group": "宝可梦 Ｘ／Ｙ",
          "text": "从古墓里挖掘出了与铜镜怪一模一样的道具，但两者之间的关系还未知。"
        },
        {
          "name": "欧米伽红宝石",
          "group": "宝可梦 欧米伽红宝石／阿尔法蓝宝石",
          "text": "过去的人们相信，铜镜怪背上的花纹里蕴藏着神秘的力量。"
        },
        {
          "name": "阿尔法蓝宝石",
          "group": "宝可梦 欧米伽红宝石／阿尔法蓝宝石",
          "text": "从古墓里挖掘出了与铜镜怪一模一样的道具，但两者之间的关系还未知。"
        }
      ]
    },
    {
      "name": "第八世代",
      "versions": [
        {
          "name": "剑",
          "group": "宝可梦 剑／盾",
          "text": "会在古老的遗迹出现。身上的纹路不属于伽勒尔文化，因此至今仍然谜团重重。"
        },
        {
          "name": "盾",
          "group": "宝可梦 剑／盾",
          "text": "虽然人们说把铜镜怪打磨到发光，它就能映照出真相，但其实它非常讨厌被打磨。"
        },
        {
          "name": "晶灿钻石",
          "group": "宝可梦 晶灿钻石／明亮珍珠",
          "text": "从古墓里挖掘出了与铜镜怪一模一样的道具，但两者之间的关系还未知。"
        },
        {
          "name": "明亮珍珠",
          "group": "宝可梦 晶灿钻石／明亮珍珠",
          "text": "为了调查它的身体构造而用Ｘ光拍摄了照片，但照片上却空无一物。"
        },
        {
          "name": "传说 阿尔宙斯",
          "group": "宝可梦传说 阿尔宙斯",
          "text": "靠着不可思议的能量漂浮在半空。人们将其背上所刻的纹路视为神圣，相同纹路有时会被刻在古时的坟墓等地。"
        }
      ]
    },
    {
      "name": "第九世代",
      "versions": [
        {
          "name": "朱",
          "group": "宝可梦 朱／紫",
          "text": "过去的人们相信，铜镜怪背上的花纹里蕴藏着神秘的力量。"
        },
        {
          "name": "紫",
          "group": "宝可梦 朱／紫",
          "text": "能在古墓找到它。据说它背上的花纹蕴藏着神秘的力量。"
        }
      ]
    }
  ],
  "evolution_chains": [
    [
      {
        "name": "铜镜怪",
        "stage": "未进化",
        "text": null,
        "image": "436Bronzor_Dream.png",
        "back_text": null,
        "from": null,
        "form_name": null
      },
      {
        "name": "青铜钟",
        "stage": "1阶进化",
        "text": "等级33以上",
        "image": "437Bronzong_Dream.png",
        "back_text": "",
        "from": "铜镜怪",
        "form_name": null
      }
    ]
  ],
  "mega_evolution": [],
  "gigantamax_evolution": [],
  "learnable_moves": [
    {
      "level": "—",
      "name": "撞击",
      "type": "一般",
      "category": "物理",
      "power": "40",
      "accuracy": "100",
      "pp": "35"
    },
    {
      "level": "—",
      "name": "念力",
      "type": "超能力",
      "category": "特殊",
      "power": "50",
      "accuracy": "100",
      "pp": "25"
    },
    {
      "level": "4",
      "name": "奇异之光",
      "type": "幽灵",
      "category": "变化",
      "power": "—",
      "accuracy": "100",
      "pp": "10"
    },
    {
      "level": "8",
      "name": "以牙还牙",
      "type": "恶",
      "category": "物理",
      "power": "50",
      "accuracy": "100",
      "pp": "10"
    },
    {
      "level": "12",
      "name": "封印",
      "type": "超能力",
      "category": "变化",
      "power": "—",
      "accuracy": "—",
      "pp": "10"
    },
    {
      "level": "16",
      "name": "陀螺球",
      "type": "钢",
      "category": "物理",
      "power": "变化",
      "accuracy": "100",
      "pp": "5"
    },
    {
      "level": "20",
      "name": "催眠术",
      "type": "超能力",
      "category": "变化",
      "power": "—",
      "accuracy": "60",
      "pp": "20"
    },
    {
      "level": "24",
      "name": "神秘守护",
      "type": "一般",
      "category": "变化",
      "power": "—",
      "accuracy": "—",
      "pp": "25"
    },
    {
      "level": "28",
      "name": "神通力",
      "type": "超能力",
      "category": "特殊",
      "power": "80",
      "accuracy": "100",
      "pp": "20"
    },
    {
      "level": "32",
      "name": "重磅冲撞",
      "type": "钢",
      "category": "物理",
      "power": "变化",
      "accuracy": "100",
      "pp": "10"
    },
    {
      "level": "36",
      "name": "铁壁",
      "type": "钢",
      "category": "变化",
      "power": "—",
      "accuracy": "—",
      "pp": "15"
    },
    {
      "level": "40",
      "name": "金属音",
      "type": "钢",
      "category": "变化",
      "power": "—",
      "accuracy": "85",
      "pp": "40"
    },
    {
      "level": "44",
      "name": "预知未来",
      "type": "超能力",
      "category": "特殊",
      "power": "120",
      "accuracy": "100",
      "pp": "10"
    }
  ],
  "machine_moves": [
    {
      "machine": "招式学习器００１",
      "name": "猛撞",
      "type": "一般",
      "category": "物理",
      "power": "90",
      "accuracy": "85",
      "pp": "20"
    },
    {
      "machine": "招式学习器００７",
      "name": "守住",
      "type": "一般",
      "category": "变化",
      "power": "—",
      "accuracy": "—",
      "pp": "10"
    },
    {
      "machine": "招式学习器０１７",
      "name": "奇异之光",
      "type": "幽灵",
      "category": "变化",
      "power": "—",
      "accuracy": "100",
      "pp": "10"
    },
    {
      "machine": "招式学习器０２３",
      "name": "充电光束",
      "type": "电",
      "category": "特殊",
      "power": "50",
      "accuracy": "90",
      "pp": "10"
    },
    {
      "machine": "招式学习器０２５",
      "name": "硬撑",
      "type": "一般",
      "category": "物理",
      "power": "70",
      "accuracy": "100",
      "pp": "20"
    },
    {
      "machine": "招式学习器０２８",
      "name": "重踏",
      "type": "地面",
      "category": "物理",
      "power": "60",
      "accuracy": "100",
      "pp": "20"
    },
    {
      "machine": "招式学习器０２９",
      "name": "祸不单行",
      "type": "幽灵",
      "category": "特殊",
      "power": "65",
      "accuracy": "100",
      "pp": "10"
    },
    {
      "machine": "招式学习器０３６",
      "name": "岩石封锁",
      "type": "岩石",
      "category": "物理",
      "power": "60",
      "accuracy": "95",
      "pp": "15"
    },
    {
      "machine": "招式学习器０４１",
      "name": "辅助力量",
      "type": "超能力",
      "category": "特殊",
      "power": "20",
      "accuracy": "100",
      "pp": "10"
    },
    {
      "machine": "招式学习器０４７",
      "name": "挺住",
      "type": "一般",
      "category": "变化",
      "power": "—",
      "accuracy": "—",
      "pp": "10"
    },
    {
      "machine": "招式学习器０４９",
      "name": "大晴天",
      "type": "火",
      "category": "变化",
      "power": "—",
      "accuracy": "—",
      "pp": "5"
    },
    {
      "machine": "招式学习器０５０",
      "name": "求雨",
      "type": "水",
      "category": "变化",
      "power": "—",
      "accuracy": "—",
      "pp": "5"
    },
    {
      "machine": "招式学习器０５１",
      "name": "沙暴",
      "type": "岩石",
      "category": "变化",
      "power": "—",
      "accuracy": "—",
      "pp": "10"
    },
    {
      "machine": "招式学习器０５４",
      "name": "精神冲击",
      "type": "超能力",
      "category": "特殊",
      "power": "80",
      "accuracy": "100",
      "pp": "10"
    },
    {
      "machine": "招式学习器０５９",
      "name": "意念头锤",
      "type": "超能力",
      "category": "物理",
      "power": "80",
      "accuracy": "90",
      "pp": "15"
    },
    {
      "machine": "招式学习器０６６",
      "name": "泰山压顶",
      "type": "一般",
      "category": "物理",
      "power": "85",
      "accuracy": "100",
      "pp": "15"
    },
    {
      "machine": "招式学习器０７０",
      "name": "梦话",
      "type": "一般",
      "category": "变化",
      "power": "—",
      "accuracy": "—",
      "pp": "10"
    },
    {
      "machine": "招式学习器０７４",
      "name": "反射壁",
      "type": "超能力",
      "category": "变化",
      "power": "—",
      "accuracy": "—",
      "pp": "20"
    },
    {
      "machine": "招式学习器０７５",
      "name": "光墙",
      "type": "超能力",
      "category": "变化",
      "power": "—",
      "accuracy": "—",
      "pp": "30"
    },
    {
      "machine": "招式学习器０７６",
      "name": "岩石爆击",
      "type": "岩石",
      "category": "物理",
      "power": "25",
      "accuracy": "90",
      "pp": "10"
    },
    {
      "machine": "招式学习器０８１",
      "name": "打草结",
      "type": "草",
      "category": "特殊",
      "power": "变化",
      "accuracy": "100",
      "pp": "20"
    },
    {
      "machine": "招式学习器０８４",
      "name": "跺脚",
      "type": "地面",
      "category": "物理",
      "power": "75",
      "accuracy": "100",
      "pp": "10"
    },
    {
      "machine": "招式学习器０８５",
      "name": "睡觉",
      "type": "超能力",
      "category": "变化",
      "power": "—",
      "accuracy": "—",
      "pp": "5"
    },
    {
      "machine": "招式学习器０８６",
      "name": "岩崩",
      "type": "岩石",
      "category": "物理",
      "power": "75",
      "accuracy": "90",
      "pp": "10"
    },
    {
      "machine": "招式学习器０９２",
      "name": "封印",
      "type": "超能力",
      "category": "变化",
      "power": "—",
      "accuracy": "—",
      "pp": "10"
    },
    {
      "machine": "招式学习器０９３",
      "name": "加农光炮",
      "type": "钢",
      "category": "特殊",
      "power": "80",
      "accuracy": "100",
      "pp": "10"
    },
    {
      "machine": "招式学习器０９８",
      "name": "特性互换",
      "type": "超能力",
      "category": "变化",
      "power": "—",
      "accuracy": "—",
      "pp": "10"
    },
    {
      "machine": "招式学习器０９９",
      "name": "铁头",
      "type": "钢",
      "category": "物理",
      "power": "80",
      "accuracy": "100",
      "pp": "15"
    },
    {
      "machine": "招式学习器１０１",
      "name": "力量宝石",
      "type": "岩石",
      "category": "特殊",
      "power": "80",
      "accuracy": "100",
      "pp": "20"
    },
    {
      "machine": "招式学习器１０３",
      "name": "替身",
      "type": "一般",
      "category": "变化",
      "power": "—",
      "accuracy": "—",
      "pp": "10"
    },
    {
      "machine": "招式学习器１０４",
      "name": "铁壁",
      "type": "钢",
      "category": "变化",
      "power": "—",
      "accuracy": "—",
      "pp": "15"
    },
    {
      "machine": "招式学习器１０９",
      "name": "戏法",
      "type": "超能力",
      "category": "变化",
      "power": "—",
      "accuracy": "100",
      "pp": "10"
    },
    {
      "machine": "招式学习器１１４",
      "name": "暗影球",
      "type": "幽灵",
      "category": "特殊",
      "power": "80",
      "accuracy": "100",
      "pp": "15"
    },
    {
      "machine": "招式学习器１１６",
      "name": "隐形岩",
      "type": "岩石",
      "category": "变化",
      "power": "—",
      "accuracy": "—",
      "pp": "20"
    },
    {
      "machine": "招式学习器１２０",
      "name": "精神强念",
      "type": "超能力",
      "category": "特殊",
      "power": "90",
      "accuracy": "100",
      "pp": "10"
    },
    {
      "machine": "招式学习器１２１",
      "name": "重磅冲撞",
      "type": "钢",
      "category": "物理",
      "power": "变化",
      "accuracy": "100",
      "pp": "10"
    },
    {
      "machine": "招式学习器１２４",
      "name": "冰旋",
      "type": "冰",
      "category": "物理",
      "power": "80",
      "accuracy": "100",
      "pp": "15"
    },
    {
      "machine": "招式学习器１２９",
      "name": "冥想",
      "type": "超能力",
      "category": "变化",
      "power": "—",
      "accuracy": "—",
      "pp": "20"
    },
    {
      "machine": "招式学习器１３０",
      "name": "帮助",
      "type": "一般",
      "category": "变化",
      "power": "—",
      "accuracy": "—",
      "pp": "20"
    },
    {
      "machine": "招式学习器１３８",
      "name": "精神场地",
      "type": "超能力",
      "category": "变化",
      "power": "—",
      "accuracy": "—",
      "pp": "10"
    },
    {
      "machine": "招式学习器１４９",
      "name": "地震",
      "type": "地面",
      "category": "物理",
      "power": "100",
      "accuracy": "100",
      "pp": "10"
    },
    {
      "machine": "招式学习器１６１",
      "name": "戏法空间",
      "type": "超能力",
      "category": "变化",
      "power": "—",
      "accuracy": "—",
      "pp": "5"
    },
    {
      "machine": "招式学习器１６８",
      "name": "日光束",
      "type": "草",
      "category": "特殊",
      "power": "120",
      "accuracy": "100",
      "pp": "10"
    },
    {
      "machine": "招式学习器１７０",
      "name": "铁蹄光线",
      "type": "钢",
      "category": "特殊",
      "power": "140",
      "accuracy": "95",
      "pp": "5"
    },
    {
      "machine": "招式学习器１７１",
      "name": "太晶爆发",
      "type": "一般",
      "category": "特殊",
      "power": "80",
      "accuracy": "100",
      "pp": "10"
    },
    {
      "machine": "招式学习器１７８",
      "name": "重力",
      "type": "超能力",
      "category": "变化",
      "power": "—",
      "accuracy": "—",
      "pp": "5"
    },
    {
      "machine": "招式学习器１８０",
      "name": "陀螺球",
      "type": "钢",
      "category": "物理",
      "power": "变化",
      "accuracy": "100",
      "pp": "5"
    },
    {
      "machine": "招式学习器２０３",
      "name": "自我暗示",
      "type": "一般",
      "category": "变化",
      "power": "—",
      "accuracy": "—",
      "pp": "10"
    },
    {
      "machine": "招式学习器２１７",
      "name": "预知未来",
      "type": "超能力",
      "category": "特殊",
      "power": "120",
      "accuracy": "100",
      "pp": "10"
    },
    {
      "machine": "招式学习器２１８",
      "name": "广域战力",
      "type": "超能力",
      "category": "特殊",
      "power": "80",
      "accuracy": "100",
      "pp": "10"
    },
    {
      "machine": "招式学习器２２３",
      "name": "金属音",
      "type": "钢",
      "category": "变化",
      "power": "—",
      "accuracy": "85",
      "pp": "40"
    }
  ],
  "egg_moves": [
    {
      "parents": [
        {
          "id": null,
          "name": "模仿香草"
        },
        {
          "id": null,
          "name": "模仿香草（道具）"
        }
      ],
      "name": "回收利用",
      "type": "一般",
      "category": "变化",
      "power": "—",
      "accuracy": "—",
      "pp": "10"
    },
    {
      "parents": [
        {
          "id": null,
          "name": "模仿香草"
        },
        {
          "id": null,
          "name": "模仿香草（道具）"
        }
      ],
      "name": "重力",
      "type": "超能力",
      "category": "变化",
      "power": "—",
      "accuracy": "—",
      "pp": "5"
    }
  ],
  "home_images": [
    {
      "name": "铜镜怪",
      "image": "0436-铜镜怪.png",
      "shiny": "0436-铜镜怪-shiny.png"
    }
  ]
}