{
    "name": "圆陆鲨",
    "profile": "圆陆鲨形似一只幼小的鲨鱼，头顶有一个巨大的鳍，头部两侧头上长着两个突起物。它全身底色深蓝，下颚到腹部呈红色，背部和头部两个突起物上都有一道浅蓝色的条纹。它有一张巨大的嘴，嘴里长着尖利的牙齿，四肢短小粗壮，且分为三趾。雄性圆陆鲨的背鳍有缺口。\n圆陆鲨曾经居住在比阿罗拉更热的热带地区，为了躲避寒冷而生活在因地热而温暖的狭窄洞窟里，这样一来就算外面刮暴风雪也不会冻着了。即便如此，一旦变冷就会和伙伴们紧紧挨在一起。它以日光照不到的洞穴为巢，要是和它一起住的话，要花很多暖气费。它潜伏在地洞内，如果有猎物或敌人经过就会从洞里扑出来大口咬住。遇到会动的东西就会扑上去将其拉回到自己住的横洞内。虽然嘴很大，但胃口却比较小。它用巨大的嘴发动的攻击威力十足，但是还不能很灵活地战斗。有时也会伤到自己，会用力过猛把牙齿豁掉，但也不太在意。锐利的牙齿即使因磨损或冲击而脱落，也能在数天内重新长出。\n",
    "forms": [
        {
            "name": "圆陆鲨",
            "index": "0443",
            "is_mega": false,
            "is_gmax": false,
            "image": "0443-圆陆鲨.png",
            "types": [
                "龙",
                "地面"
            ],
            "genus": "陆鲨宝可梦",
            "ability": [
                {
                    "name": "沙隐",
                    "is_hidden": false
                },
                {
                    "name": "粗糙皮肤",
                    "is_hidden": true
                }
            ],
            "experience": {
                "number": "1,250,000",
                "speed": "慢"
            },
            "height": "0.7m",
            "weight": "20.5kg",
            "gender_rate": {
                "male": "50%",
                "female": "50%"
            },
            "shape": "双足兽形",
            "color": "蓝色",
            "catch_rate": {
                "number": "45",
                "rate": "5.9%"
            },
            "egg_groups": [
                "怪兽",
                "龙"
            ]
        }
    ],
    "stats": [
        {
            "form": "一般",
            "data": {
                "hp": "58",
                "attack": "70",
                "defense": "45",
                "sp_attack": "40",
                "sp_defense": "45"
            }
        }
    ],
    "flavor_texts": [
        {
            "name": "第一世代",
            "versions": []
        },
        {
            "name": "第二世代",
            "versions": []
        },
        {
            "name": "第三世代",
            "versions": []
        },
        {
            "name": "第四世代",
            "versions": [
                {
                    "name": "钻石",
                    "group": "宝可梦 钻石／珍珠",
                    "text": "把洞窟里的小横洞作为住所。如果有猎物靠近，就会迅速扑出来捕捉。"
                },
                {
                    "name": "珍珠",
                    "group": "宝可梦 钻石／珍珠",
                    "text": "曾经居住在热带地区。为了躲避寒冷而在有地热的温暖洞窟里生活。"
                },
                {
                    "name": "白金",
                    "group": "宝可梦 白金",
                    "text": "用巨大的嘴发动攻击威力十足，但是还不能很灵活地战斗，也会伤到自己。*"
                },
                {
                    "name": "心金",
                    "group": "宝可梦 心金／魂银",
                    "text": "生活在被地热加温的横洞里。如果有敌人靠近，就会从洞里扑出来，大口咬住。"
                },
                {
                    "name": "魂银",
                    "group": "宝可梦 心金／魂银",
                    "text": "生活在被地热加温的横洞里。如果有敌人靠近，就会从洞里扑出来，大口咬住。"
                }
            ]
        },
        {
            "name": "第五世代",
            "versions": [
                {
                    "name": "黑",
                    "group": "宝可梦 黑／白",
                    "text": "用巨大的嘴发动攻击威力十足，但是还不能很灵活地战斗，也会伤到自己。*"
                },
                {
                    "name": "白",
                    "group": "宝可梦 黑／白",
                    "text": "用巨大的嘴发动攻击威力十足，但是还不能很灵活地战斗，也会伤到自己。*"
                },
                {
                    "name": "黑２",
                    "group": "宝可梦 黑２／白２",
                    "text": "用巨大的嘴发动攻击威力十足，但是还不能很灵活地战斗，也会伤到自己。*"
                },
                {
                    "name": "白２",
                    "group": "宝可梦 黑２／白２",
                    "text": "用巨大的嘴发动攻击威力十足，但是还不能很灵活地战斗，也会伤到自己。*"
                }
            ]
        },
        {
            "name": "第六世代",
            "versions": [
                {
                    "name": "Ｘ",
                    "group": "宝可梦 Ｘ／Ｙ",
                    "text": "生活在被地热加温的横洞里。如果有敌人靠近，就会从洞里扑出来，大口咬住。"
                },
                {
                    "name": "Ｙ",
                    "group": "宝可梦 Ｘ／Ｙ",
                    "text": "把洞窟里的小横洞作为住所。如果有猎物靠近，就会迅速扑出来捕捉。"
                },
                {
                    "name": "欧米伽红宝石",
                    "group": "宝可梦 欧米伽红宝石／阿尔法蓝宝石",
                    "text": "生活在被地热加温的横洞里。如果有敌人靠近，就会从洞里扑出来，大口咬住。"
                },
                {
                    "name": "阿尔法蓝宝石",
                    "group": "宝可梦 欧米伽红宝石／阿尔法蓝宝石",
                    "text": "把洞窟里的小横洞作为住所。如果有猎物靠近，就会迅速扑出来捕捉。"
                }
            ]
        },
        {
            "name": "第七世代",
            "versions": [
                {
                    "name": "太阳",
                    "group": "精灵宝可梦 太阳／月亮",
                    "text": "生活在因地热而温暖的洞窟里。即便如此，一旦变冷就会和伙伴们紧紧挨在一起。"
                },
                {
                    "name": "月亮",
                    "group": "精灵宝可梦 太阳／月亮",
                    "text": "潜伏在地洞内，如果有猎物或敌人经过，就会扑出来咬住。有时会用力过猛牙齿豁掉。"
                },
                {
                    "name": "究极之日",
                    "group": "精灵宝可梦 究极之日／究极之月",
                    "text": "会对动的东西发生反应，飞扑过去咬住。有时候会伤到自己，但也不太在意。"
                },
                {
                    "name": "究极之月",
                    "group": "精灵宝可梦 究极之日／究极之月",
                    "text": "原本栖息在比阿罗拉更热的地方。一起住的话，要花很多暖气费。"
                }
            ]
        },
        {
            "name": "第八世代",
            "versions": [
                {
                    "name": "剑",
                    "group": "宝可梦 剑／盾",
                    "text": "喜欢因地热而温暖的狭窄横洞，这样一来就算外面刮暴风雪也不会冻着了。"
                },
                {
                    "name": "盾",
                    "group": "宝可梦 剑／盾",
                    "text": "遇到会动的东西就会扑上去将其拉回到自己住的横洞内。虽然嘴很大，但胃口却比较小。"
                },
                {
                    "name": "晶灿钻石",
                    "group": "宝可梦 晶灿钻石／明亮珍珠",
                    "text": "把洞窟里的小横洞作为住所。如果有猎物靠近，就会迅速扑出来捕捉。"
                },
                {
                    "name": "明亮珍珠",
                    "group": "宝可梦 晶灿钻石／明亮珍珠",
                    "text": "曾经居住在热带地区。为了躲避寒冷而在有地热的温暖洞窟里生活。"
                },
                {
                    "name": "传说 阿尔宙斯",
                    "group": "宝可梦传说 阿尔宙斯",
                    "text": "以日光照不到的洞穴为巢。锐利的牙齿即使因磨损或冲击而脱落，也能在数天内重新长出。"
                }
            ]
        },
        {
            "name": "第九世代",
            "versions": [
                {
                    "name": "朱",
                    "group": "宝可梦 朱／紫",
                    "text": "潜伏在地洞内，如果有猎物或敌人经过，就会扑出来咬住。有时会用力过猛牙齿豁掉。"
                },
                {
                    "name": "紫",
                    "group": "宝可梦 朱／紫",
                    "text": "生活在被地热加温的横洞里。如果有敌人靠近，就会从洞里扑出来，大口咬住。"
                }
            ]
        }
    ],
    "evolution_chains": [
        [
            {
                "name": "圆陆鲨",
                "stage": "未进化",
                "text": null,
                "image": "443Gible_Dream.png",
                "back_text": null,
                "from": null,
                "form_name": null
            },
            {
                "name": "尖牙陆鲨",
                "stage": "1阶进化",
                "text": "等级24以上",
                "image": "444Gabite_Dream.png",
                "back_text": "",
                "from": "圆陆鲨",
                "form_name": null
            },
            {
                "name": "烈咬陆鲨",
                "stage": "2阶进化",
                "text": "等级48以上",
                "image": "445Garchomp_Dream.png",
                "back_text": "",
                "from": "尖牙陆鲨",
                "form_name": null
            }
        ]
    ],
    "names": {
        "zh_hans": "圆陆鲨",
        "zh_hant": "圓陸鯊",
        "en": "Gible",
        "fr": "Gible",
        "de": "Kaumalat",
        "it": "Gible",
        "es": "Gible",
        "ja": "フカマル",
        "ko": "딥상어동"
    },
    "moves": {
        "learned": [
            {
                "form": "一般",
                "data": [
                    {
                        "level_learned_at": "—",
                        "machine_used": null,
                        "method": "提升等级",
                        "name": "撞击",
                        "flavor_text": "用整个身体撞向对手进行攻击。",
                        "type": "一般",
                        "category": "物理",
                        "power": "40",
                        "accuracy": "100",
                        "pp": "35"
                    },
                    {
                        "level_learned_at": "—",
                        "machine_used": null,
                        "method": "提升等级",
                        "name": "流沙深渊",
                        "flavor_text": "将对手困在铺天盖地的沙暴中，在４～５回合内进行攻击。",
                        "type": "地面",
                        "category": "物理",
                        "power": "35",
                        "accuracy": "85",
                        "pp": "15"
                    },
                    {
                        "level_learned_at": "6",
                        "machine_used": null,
                        "method": "提升等级",
                        "name": "泼沙",
                        "flavor_text": "向对手脸上泼沙子，从而降低命中率。",
                        "type": "地面",
                        "category": "变化",
                        "power": "—",
                        "accuracy": "100",
                        "pp": "15"
                    },
                    {
                        "level_learned_at": "12",
                        "machine_used": null,
                        "method": "提升等级",
                        "name": "龙息",
                        "flavor_text": "将强烈的气息吹向对手进行攻击。有时会让对手陷入麻痹状态。",
                        "type": "龙",
                        "category": "特殊",
                        "power": "60",
                        "accuracy": "100",
                        "pp": "20"
                    },
                    {
                        "level_learned_at": "18",
                        "machine_used": null,
                        "method": "提升等级",
                        "name": "重踏",
                        "flavor_text": "用力踩踏地面并攻击自己周围所有的宝可梦。会降低对方的速度。",
                        "type": "地面",
                        "category": "物理",
                        "power": "60",
                        "accuracy": "100",
                        "pp": "20"
                    },
                    {
                        "level_learned_at": "25",
                        "machine_used": null,
                        "method": "提升等级",
                        "name": "咬住",
                        "flavor_text": "用尖锐的牙咬住对手进行攻击。有时会使对手畏缩。",
                        "type": "恶",
                        "category": "物理",
                        "power": "60",
                        "accuracy": "100",
                        "pp": "25"
                    },
                    {
                        "level_learned_at": "30",
                        "machine_used": null,
                        "method": "提升等级",
                        "name": "劈开",
                        "flavor_text": "用爪子或镰刀等劈开对手进行攻击。容易击中要害。",
                        "type": "一般",
                        "category": "物理",
                        "power": "70",
                        "accuracy": "100",
                        "pp": "20"
                    },
                    {
                        "level_learned_at": "36",
                        "machine_used": null,
                        "method": "提升等级",
                        "name": "龙爪",
                        "flavor_text": "用尖锐的巨爪劈开对手进行攻击。",
                        "type": "龙",
                        "category": "物理",
                        "power": "80",
                        "accuracy": "100",
                        "pp": "15"
                    },
                    {
                        "level_learned_at": "42",
                        "machine_used": null,
                        "method": "提升等级",
                        "name": "挖洞",
                        "flavor_text": "第１回合钻入地底，第２回合攻击对手。",
                        "type": "地面",
                        "category": "物理",
                        "power": "80",
                        "accuracy": "100",
                        "pp": "10"
                    },
                    {
                        "level_learned_at": "48",
                        "machine_used": null,
                        "method": "提升等级",
                        "name": "沙暴",
                        "flavor_text": "在５回合内扬起沙暴，除岩石、地面和钢属性以外的宝可梦，都会受到伤害。岩石属性的特防还会提高。",
                        "type": "岩石",
                        "category": "变化",
                        "power": "—",
                        "accuracy": "—",
                        "pp": "10"
                    },
                    {
                        "level_learned_at": "54",
                        "machine_used": null,
                        "method": "提升等级",
                        "name": "猛撞",
                        "flavor_text": "以惊人的气势撞向对手进行攻击。自己也会受到少许伤害。",
                        "type": "一般",
                        "category": "物理",
                        "power": "90",
                        "accuracy": "85",
                        "pp": "20"
                    },
                    {
                        "level_learned_at": "60",
                        "machine_used": null,
                        "method": "提升等级",
                        "name": "龙之俯冲",
                        "flavor_text": "释放出骇人的杀气，一边威慑一边撞击对手。有时会使对手畏缩。",
                        "type": "龙",
                        "category": "物理",
                        "power": "100",
                        "accuracy": "75",
                        "pp": "10"
                    }
                ]
            }
        ],
        "machine": [
            {
                "form": "一般",
                "data": [
                    {
                        "level_learned_at": null,
                        "machine_used": "招式学习器００１",
                        "method": "招式学习器",
                        "name": "猛撞",
                        "flavor_text": "以惊人的气势撞向对手进行攻击。自己也会受到少许伤害。",
                        "type": "一般",
                        "class": "物理",
                        "power": "90",
                        "accuracy": "85",
                        "pp": "20"
                    },
                    {
                        "level_learned_at": null,
                        "machine_used": "招式学习器００６",
                        "method": "招式学习器",
                        "name": "可怕面孔",
                        "flavor_text": "用恐怖的表情瞪着对手，使其害怕，从而大幅降低对手的速度。",
                        "type": "一般",
                        "class": "变化",
                        "power": "—",
                        "accuracy": "100",
                        "pp": "10"
                    },
                    {
                        "level_learned_at": null,
                        "machine_used": "招式学习器００７",
                        "method": "招式学习器",
                        "name": "守住",
                        "flavor_text": "完全抵挡对手的攻击。连续使出则容易失败。",
                        "type": "一般",
                        "class": "变化",
                        "power": "—",
                        "accuracy": "—",
                        "pp": "10"
                    },
                    {
                        "level_learned_at": null,
                        "machine_used": "招式学习器００８",
                        "method": "招式学习器",
                        "name": "火焰牙",
                        "flavor_text": "用覆盖着火焰的牙齿咬住对手。有时会使对手畏缩或陷入灼伤状态。",
                        "type": "火",
                        "class": "物理",
                        "power": "65",
                        "accuracy": "95",
                        "pp": "15"
                    },
                    {
                        "level_learned_at": null,
                        "machine_used": "招式学习器００９",
                        "method": "招式学习器",
                        "name": "雷电牙",
                        "flavor_text": "用蓄满电流的牙齿咬住对手。有时会使对手畏缩或陷入麻痹状态。",
                        "type": "电",
                        "class": "物理",
                        "power": "65",
                        "accuracy": "95",
                        "pp": "15"
                    },
                    {
                        "level_learned_at": null,
                        "machine_used": "招式学习器０２５",
                        "method": "招式学习器",
                        "name": "硬撑",
                        "flavor_text": "当自己处于中毒、麻痹、灼伤状态时，向对手使出此招式的话，威力会变成２倍。",
                        "type": "一般",
                        "class": "物理",
                        "power": "70",
                        "accuracy": "100",
                        "pp": "20"
                    },
                    {
                        "level_learned_at": null,
                        "machine_used": "招式学习器０２８",
                        "method": "招式学习器",
                        "name": "重踏",
                        "flavor_text": "用力踩踏地面并攻击自己周围所有的宝可梦。会降低对方的速度。",
                        "type": "地面",
                        "class": "物理",
                        "power": "60",
                        "accuracy": "100",
                        "pp": "20"
                    },
                    {
                        "level_learned_at": null,
                        "machine_used": "招式学习器０３１",
                        "method": "招式学习器",
                        "name": "金属爪",
                        "flavor_text": "用钢铁之爪劈开对手进行攻击。有时会提高自己的攻击。",
                        "type": "钢",
                        "class": "物理",
                        "power": "50",
                        "accuracy": "95",
                        "pp": "35"
                    },
                    {
                        "level_learned_at": null,
                        "machine_used": "招式学习器０３２",
                        "method": "招式学习器",
                        "name": "高速星星",
                        "flavor_text": "发射星形的光攻击对手。攻击必定会命中。",
                        "type": "一般",
                        "class": "特殊",
                        "power": "60",
                        "accuracy": "—",
                        "pp": "20"
                    },
                    {
                        "level_learned_at": null,
                        "machine_used": "招式学习器０３５",
                        "method": "招式学习器",
                        "name": "泥巴射击",
                        "flavor_text": "向对手投掷泥块进行攻击。同时降低对手的速度。",
                        "type": "地面",
                        "class": "特殊",
                        "power": "55",
                        "accuracy": "95",
                        "pp": "15"
                    },
                    {
                        "level_learned_at": null,
                        "machine_used": "招式学习器０３６",
                        "method": "招式学习器",
                        "name": "岩石封锁",
                        "flavor_text": "投掷岩石进行攻击。封住对手的行动，从而降低速度。",
                        "type": "岩石",
                        "class": "物理",
                        "power": "60",
                        "accuracy": "95",
                        "pp": "15"
                    },
                    {
                        "level_learned_at": null,
                        "machine_used": "招式学习器０４４",
                        "method": "招式学习器",
                        "name": "龙尾",
                        "flavor_text": "弹飞对手，强制拉后备宝可梦上场。如果对手为野生宝可梦，战斗将直接结束。",
                        "type": "龙",
                        "class": "物理",
                        "power": "60",
                        "accuracy": "90",
                        "pp": "10"
                    },
                    {
                        "level_learned_at": null,
                        "machine_used": "招式学习器０４７",
                        "method": "招式学习器",
                        "name": "挺住",
                        "flavor_text": "即使受到攻击，也至少会留下１ＨＰ。连续使出则容易失败。",
                        "type": "一般",
                        "class": "变化",
                        "power": "—",
                        "accuracy": "—",
                        "pp": "10"
                    },
                    {
                        "level_learned_at": null,
                        "machine_used": "招式学习器０４９",
                        "method": "招式学习器",
                        "name": "大晴天",
                        "flavor_text": "在５回合内让日照变得强烈，从而提高火属性的招式威力。水属性的招式威力则降低。",
                        "type": "火",
                        "class": "变化",
                        "power": "—",
                        "accuracy": "—",
                        "pp": "5"
                    },
                    {
                        "level_learned_at": null,
                        "machine_used": "招式学习器０５０",
                        "method": "招式学习器",
                        "name": "求雨",
                        "flavor_text": "在５回合内一直降雨，从而提高水属性的招式威力。火属性的招式威力则降低。",
                        "type": "水",
                        "class": "变化",
                        "power": "—",
                        "accuracy": "—",
                        "pp": "5"
                    },
                    {
                        "level_learned_at": null,
                        "machine_used": "招式学习器０５１",
                        "method": "招式学习器",
                        "name": "沙暴",
                        "flavor_text": "在５回合内扬起沙暴，除岩石、地面和钢属性以外的宝可梦，都会受到伤害。岩石属性的特防还会提高。",
                        "type": "岩石",
                        "class": "变化",
                        "power": "—",
                        "accuracy": "—",
                        "pp": "10"
                    },
                    {
                        "level_learned_at": null,
                        "machine_used": "招式学习器０５５",
                        "method": "招式学习器",
                        "name": "挖洞",
                        "flavor_text": "第１回合钻入地底，第２回合攻击对手。",
                        "type": "地面",
                        "class": "物理",
                        "power": "80",
                        "accuracy": "100",
                        "pp": "10"
                    },
                    {
                        "level_learned_at": null,
                        "machine_used": "招式学习器０５７",
                        "method": "招式学习器",
                        "name": "点到为止",
                        "flavor_text": "对手的ＨＰ至少会留下１ＨＰ，如此般手下留情地攻击。",
                        "type": "一般",
                        "class": "物理",
                        "power": "40",
                        "accuracy": "100",
                        "pp": "40"
                    },
                    {
                        "level_learned_at": null,
                        "machine_used": "招式学习器０６１",
                        "method": "招式学习器",
                        "name": "暗影爪",
                        "flavor_text": "以影子做成的锐爪，劈开对手。容易击中要害。",
                        "type": "幽灵",
                        "class": "物理",
                        "power": "70",
                        "accuracy": "100",
                        "pp": "15"
                    },
                    {
                        "level_learned_at": null,
                        "machine_used": "招式学习器０６６",
                        "method": "招式学习器",
                        "name": "泰山压顶",
                        "flavor_text": "用整个身体压住对手进行攻击。有时会让对手陷入麻痹状态。",
                        "type": "一般",
                        "class": "物理",
                        "power": "85",
                        "accuracy": "100",
                        "pp": "15"
                    },
                    {
                        "level_learned_at": null,
                        "machine_used": "招式学习器０７０",
                        "method": "招式学习器",
                        "name": "梦话",
                        "flavor_text": "从自己已学会的招式中任意使出１个。只能在自己睡觉时使用。",
                        "type": "一般",
                        "class": "变化",
                        "power": "—",
                        "accuracy": "—",
                        "pp": "10"
                    },
                    {
                        "level_learned_at": null,
                        "machine_used": "招式学习器０７８",
                        "method": "招式学习器",
                        "name": "龙爪",
                        "flavor_text": "用尖锐的巨爪劈开对手进行攻击。",
                        "type": "龙",
                        "class": "物理",
                        "power": "80",
                        "accuracy": "100",
                        "pp": "15"
                    },
                    {
                        "level_learned_at": null,
                        "machine_used": "招式学习器０８５",
                        "method": "招式学习器",
                        "name": "睡觉",
                        "flavor_text": "连续睡上２回合。回复自己的全部ＨＰ以及治愈所有异常状态。",
                        "type": "超能力",
                        "class": "变化",
                        "power": "—",
                        "accuracy": "—",
                        "pp": "5"
                    },
                    {
                        "level_learned_at": null,
                        "machine_used": "招式学习器０８６",
                        "method": "招式学习器",
                        "name": "岩崩",
                        "flavor_text": "将大岩石猛烈地撞向对手进行攻击。有时会使对手畏缩。",
                        "type": "岩石",
                        "class": "物理",
                        "power": "75",
                        "accuracy": "90",
                        "pp": "10"
                    },
                    {
                        "level_learned_at": null,
                        "machine_used": "招式学习器０８８",
                        "method": "招式学习器",
                        "name": "剑舞",
                        "flavor_text": "激烈地跳起战舞提高气势。大幅提高自己的攻击。",
                        "type": "一般",
                        "class": "变化",
                        "power": "—",
                        "accuracy": "—",
                        "pp": "20"
                    },
                    {
                        "level_learned_at": null,
                        "machine_used": "招式学习器０９９",
                        "method": "招式学习器",
                        "name": "铁头",
                        "flavor_text": "用钢铁般坚硬的头部进行攻击。有时会使对手畏缩。",
                        "type": "钢",
                        "class": "物理",
                        "power": "80",
                        "accuracy": "100",
                        "pp": "15"
                    },
                    {
                        "level_learned_at": null,
                        "machine_used": "招式学习器１０３",
                        "method": "招式学习器",
                        "name": "替身",
                        "flavor_text": "削减少许自己的ＨＰ，制造分身。分身将成为自己的替身。",
                        "type": "一般",
                        "class": "变化",
                        "power": "—",
                        "accuracy": "—",
                        "pp": "10"
                    },
                    {
                        "level_learned_at": null,
                        "machine_used": "招式学习器１１５",
                        "method": "招式学习器",
                        "name": "龙之波动",
                        "flavor_text": "从大大的口中掀起冲击波攻击对手。",
                        "type": "龙",
                        "class": "特殊",
                        "power": "85",
                        "accuracy": "100",
                        "pp": "10"
                    },
                    {
                        "level_learned_at": null,
                        "machine_used": "招式学习器１１６",
                        "method": "招式学习器",
                        "name": "隐形岩",
                        "flavor_text": "将无数岩石悬浮在对手的周围，从而对替换出场的对手的宝可梦给予伤害。",
                        "type": "岩石",
                        "class": "变化",
                        "power": "—",
                        "accuracy": "—",
                        "pp": "20"
                    },
                    {
                        "level_learned_at": null,
                        "machine_used": "招式学习器１２５",
                        "method": "招式学习器",
                        "name": "喷射火焰",
                        "flavor_text": "向对手发射烈焰进行攻击。有时会让对手陷入灼伤状态。",
                        "type": "火",
                        "class": "特殊",
                        "power": "90",
                        "accuracy": "100",
                        "pp": "15"
                    },
                    {
                        "level_learned_at": null,
                        "machine_used": "招式学习器１３０",
                        "method": "招式学习器",
                        "name": "帮助",
                        "flavor_text": "帮助伙伴。被帮助的宝可梦，其招式威力变得比平时大。",
                        "type": "一般",
                        "class": "变化",
                        "power": "—",
                        "accuracy": "—",
                        "pp": "20"
                    },
                    {
                        "level_learned_at": null,
                        "machine_used": "招式学习器１３３",
                        "method": "招式学习器",
                        "name": "大地之力",
                        "flavor_text": "向对手脚下释放出大地之力。有时会降低对手的特防。",
                        "type": "地面",
                        "class": "特殊",
                        "power": "90",
                        "accuracy": "100",
                        "pp": "10"
                    },
                    {
                        "level_learned_at": null,
                        "machine_used": "招式学习器１４１",
                        "method": "招式学习器",
                        "name": "大字爆炎",
                        "flavor_text": "用大字形状的火焰烧尽对手。有时会让对手陷入灼伤状态。",
                        "type": "火",
                        "class": "特殊",
                        "power": "110",
                        "accuracy": "85",
                        "pp": "5"
                    },
                    {
                        "level_learned_at": null,
                        "machine_used": "招式学习器１４９",
                        "method": "招式学习器",
                        "name": "地震",
                        "flavor_text": "利用地震的冲击，攻击自己周围所有的宝可梦。",
                        "type": "地面",
                        "class": "物理",
                        "power": "100",
                        "accuracy": "100",
                        "pp": "10"
                    },
                    {
                        "level_learned_at": null,
                        "machine_used": "招式学习器１５０",
                        "method": "招式学习器",
                        "name": "尖石攻击",
                        "flavor_text": "用尖尖的岩石刺入对手进行攻击。容易击中要害。",
                        "type": "岩石",
                        "class": "物理",
                        "power": "100",
                        "accuracy": "80",
                        "pp": "5"
                    },
                    {
                        "level_learned_at": null,
                        "machine_used": "招式学习器１５６",
                        "method": "招式学习器",
                        "name": "逆鳞",
                        "flavor_text": "在２～３回合内，乱打一气地进行攻击。大闹一番后自己会陷入混乱。",
                        "type": "龙",
                        "class": "物理",
                        "power": "120",
                        "accuracy": "100",
                        "pp": "10"
                    },
                    {
                        "level_learned_at": null,
                        "machine_used": "招式学习器１６９",
                        "method": "招式学习器",
                        "name": "流星群",
                        "flavor_text": "从天空中向对手落下陨石。使用之后因为反作用力，自己的特攻会大幅降低。",
                        "type": "龙",
                        "class": "特殊",
                        "power": "130",
                        "accuracy": "90",
                        "pp": "5"
                    },
                    {
                        "level_learned_at": null,
                        "machine_used": "招式学习器１７１",
                        "method": "招式学习器",
                        "name": "太晶爆发",
                        "flavor_text": "太晶化时，会放出太晶属性的能量攻击。比较自己的攻击和特攻，用数值相对较高的一项给予对方伤害。（其他属性）／用攻击和特攻数值较高的一项给予伤害。对正处于太晶化的对手效果绝佳。自己的攻击和特攻会降低。（星晶）",
                        "type": "一般",
                        "class": "特殊",
                        "power": "80",
                        "accuracy": "100",
                        "pp": "10"
                    },
                    {
                        "level_learned_at": null,
                        "machine_used": "招式学习器１７６",
                        "method": "招式学习器",
                        "name": "流沙深渊",
                        "flavor_text": "将对手困在铺天盖地的沙暴中，在４～５回合内进行攻击。",
                        "type": "地面",
                        "class": "物理",
                        "power": "35",
                        "accuracy": "85",
                        "pp": "15"
                    },
                    {
                        "level_learned_at": null,
                        "machine_used": "招式学习器２００",
                        "method": "招式学习器",
                        "name": "鳞射",
                        "flavor_text": "发射鳞片进行攻击。连续攻击２～５次。速度会提高但防御会降低。",
                        "type": "龙",
                        "class": "物理",
                        "power": "25",
                        "accuracy": "90",
                        "pp": "20"
                    },
                    {
                        "level_learned_at": null,
                        "machine_used": "招式学习器２０４",
                        "method": "招式学习器",
                        "name": "舍身冲撞",
                        "flavor_text": "拼命地猛撞向对手进行攻击。自己也会受到不小的伤害。",
                        "type": "一般",
                        "class": "物理",
                        "power": "120",
                        "accuracy": "100",
                        "pp": "15"
                    },
                    {
                        "level_learned_at": null,
                        "machine_used": "招式学习器２１５",
                        "method": "招式学习器",
                        "name": "热沙大地",
                        "flavor_text": "将滚烫的沙子砸向对手进行攻击。有时会让对手陷入灼伤状态。",
                        "type": "地面",
                        "class": "特殊",
                        "power": "70",
                        "accuracy": "100",
                        "pp": "10"
                    },
                    {
                        "level_learned_at": null,
                        "machine_used": "招式学习器２２６",
                        "method": "招式学习器",
                        "name": "龙声鼓舞",
                        "flavor_text": "以龙之鼓舞提高士气，让我方的招式变得容易击中要害。对龙属性的鼓舞效果会更强。",
                        "type": "龙",
                        "class": "变化",
                        "power": "—",
                        "accuracy": "—",
                        "pp": "15"
                    }
                ]
            }
        ]
    },
    "home_images": [
        {
            "name": "圆陆鲨-雄性",
            "image": "0443-圆陆鲨-雄性.png",
            "shiny": "0443-圆陆鲨-雄性-shiny.png"
        },
        {
            "name": "圆陆鲨-雌性",
            "image": "0443-圆陆鲨-雌性.png",
            "shiny": "0443-圆陆鲨-雌性-shiny.png"
        }
    ]
}