{
    "index": "690",
    "generation": "第七世代",
    "name": "鸟嘴加农炮",
    "name_jp": "くちばしキャノン",
    "name_en": "Beak Blast",
    "type": "飞行",
    "category": "物理",
    "power": "100",
    "accuracy": "100",
    "pp": "15",
    "text": "先加热鸟嘴后再进行攻击。鸟嘴在加热时对手触碰的话，就会使其灼伤。",
    "effect": "在一回合内，先加热鸟嘴，再攻击目标造成伤害。\n加热鸟嘴的动作优先度为+5，进行攻击的优先度为-3。如果在加热鸟嘴到发动攻击期间受到接触类招式攻击，伤害的施加者陷入灼伤状态。\n该招式不能被鹦鹉学舌学习，也不会被借助、挥指、梦话或号令发动。\n鸟嘴加农炮攻击对防弹特性的宝可梦无效，但不能免疫灼伤状态。\n",
    "info": [
        "不是接触类招式",
        "受守住影响",
        "不受魔法反射影响",
        "不可以被抢夺",
        "不受鹦鹉学舌影响",
        "受王者之证等类似道具影响"
    ],
    "range": "除自身以外场上一只可以攻击到的宝可梦",
    "pokemon": {
        "level": [
            {
                "index": "0733",
                "name": "铳嘴大鸟"
            }
        ],
        "machine": [],
        "egg": [],
        "tutor": []
    }
}