{
    "index": "090",
    "generation": "第四世代",
    "name": "毒疗",
    "name_jp": "ポイズンヒール",
    "name_en": "Poison Heal",
    "text": "变为中毒状态时，ＨＰ不会减少，反而会增加起来。",
    "common_count": 2,
    "hidden_count": 1,
    "effect": "在中毒和剧毒状态下，ＨＰ不会因为中毒而减少；每回合回复最大ＨＰ的1⁄8。\n剧毒状态的伤害计数会在每次行动后增加，失去毒疗特性后剧毒状态的伤害计数不会重置。\n",
    "info": [
        "可以被交换",
        "可以被其他特性覆盖",
        "可以被其他宝可梦复制",
        "受无特性状态影响",
        "变身时特性有效",
        "不在入场时发动"
    ],
    "pokemon": [
        {
            "index": "0285",
            "name": "蘑蘑菇",
            "types": [
                "草"
            ],
            "first": "孢子",
            "second": "毒疗",
            "hidden": "飞毛腿"
        },
        {
            "index": "0286",
            "name": "斗笠菇",
            "types": [
                "草",
                "格斗"
            ],
            "first": "孢子",
            "second": "毒疗",
            "hidden": "技术高手"
        },
        {
            "index": "0472",
            "name": "天蝎王",
            "types": [
                "地面",
                "飞行"
            ],
            "first": "怪力钳",
            "second": "沙隐",
            "hidden": "毒疗"
        }
    ]
}